fnlength/__init__.py
fnlength/dir_travel.py
fnlength/file_travel.py
fnlength/main.py
fnlength-1.0.0.dist-info/LICENSE
fnlength-1.0.0.dist-info/METADATA
fnlength-1.0.0.dist-info/WHEEL
fnlength-1.0.0.dist-info/top_level.txt
fnlength-1.0.0.dist-info/RECORD
