Metadata-Version: 2.1
Name: fnlength
Version: 1.0.0
Summary: Python filename length script
Home-page: https://github.com/IgorMan2005/fnlength
Author: IgorMan (IgorMan2005)
Author-email: igorman2005@gmail.com
Project-URL: Documentation, https://best-itpro.ru/news/fnlength/
Keywords: python filename length script filenamelength fnlength
Classifier: Programming Language :: Python :: 3.9
Classifier: License :: OSI Approved :: MIT License
Classifier: Operating System :: OS Independent
Requires-Python: >=3.6
License-File: LICENSE
